CHANGES.txt
LICENSE.txt
MANIFEST.in
README
requirements.txt
setup.py
pitchfork/__init__.py
pitchfork/pitchfork.py
pitchfork.egg-info/PKG-INFO
pitchfork.egg-info/SOURCES.txt
pitchfork.egg-info/dependency_links.txt
pitchfork.egg-info/requires.txt
pitchfork.egg-info/top_level.txt
tests/__init__.py
tests/test_pitchfork.py