Metadata-Version: 1.1
Name: pitchfork
Version: v0.1.4
Summary: Unofficial API for pitchfork.com reviews
Home-page: http://pypi.python.org/pypi/pitchfork/
Author: Michal Czaplinski
Author-email: mmczaplinski@gmail.com
License: LICENSE.txt
Platform: UNKNOWN
Classifier: License :: OSI Approved :: MIT License
Classifier: Programming Language :: Python
Classifier: Programming Language :: Python :: 3
Classifier: Programming Language :: Python :: 3.0
Classifier: Programming Language :: Python :: 3.1
Classifier: Programming Language :: Python :: 3.2
Classifier: Programming Language :: Python :: 3.3
Classifier: Programming Language :: Python :: 3.4
Classifier: Topic :: Internet :: WWW/HTTP :: Browsers
Classifier: Topic :: Internet :: WWW/HTTP :: Indexing/Search
Classifier: Topic :: Multimedia :: Sound/Audio
Classifier: Topic :: Utilities
